aioreactive/__init__.py
aioreactive/_version.py
aioreactive/combine.py
aioreactive/create.py
aioreactive/filtering.py
aioreactive/iterable/__init__.py
aioreactive/iterable/to_async_observable.py
aioreactive/leave.py
aioreactive/msg.py
aioreactive/notification.py
aioreactive/observables.py
aioreactive/observers.py
aioreactive/py.typed
aioreactive/subject.py
aioreactive/subscription.py
aioreactive/testing/__init__.py
aioreactive/testing/observer.py
aioreactive/testing/subject.py
aioreactive/testing/utils.py
aioreactive/testing/virtual_events.py
aioreactive/timeshift.py
aioreactive/transform.py
aioreactive/types.py
aioreactive/utils.py
aioreactive-0.20.0.dist-info/LICENSE.txt
aioreactive-0.20.0.dist-info/METADATA
aioreactive-0.20.0.dist-info/WHEEL
aioreactive-0.20.0.dist-info/RECORD
