Metadata-Version: 2.1
Name: aioreactive
Version: 0.20.0
Summary: sync/await Reactive Tools for Python 3.10+
Home-page: https://github.com/dbrattli/aioreactive
License: MIT
Author: Dag Brattli
Author-email: dag@brattli.net
Requires-Python: >=3.10,<4
Classifier: Development Status :: 3 - Alpha
Classifier: Environment :: Other Environment
Classifier: Intended Audience :: Developers
Classifier: License :: OSI Approved :: MIT License
Classifier: Operating System :: OS Independent
Classifier: Programming Language :: Python :: 3
Classifier: Programming Language :: Python :: 3.10
Classifier: Programming Language :: Python :: 3.11
Classifier: Programming Language :: Python :: 3.12
Classifier: Programming Language :: Python :: Implementation :: CPython
Classifier: Topic :: Software Development :: Libraries :: Python Modules
Requires-Dist: Expression (>=5.3.0,<6.0.0)
Requires-Dist: reactivex (>=4.0.0,<5.0.0)
Requires-Dist: typing-extensions (>=4.1.1,<5.0.0)
Project-URL: Repository, https://github.com/dbrattli/aioreactive
